Metadata-Version: 2.1
Name: pearpy
Version: 0.1.3
Summary: A Python package for writing multithreaded code.
Home-page: https://github.com/MLH-Fellowship/pear
Author: Aiden Szeto
Author-email: aszeto35@gmail.com
License: MIT
Download-URL: https://github.com/MLH-Fellowship/pear/archive/refs/tags/v0.1.3.tar.gz
Keywords: multithreading,parallelism,processes
Platform: UNKNOWN
Classifier: Development Status :: 3 - Alpha
Classifier: Intended Audience :: Developers
Classifier: Topic :: Software Development :: Build Tools
Classifier: License :: OSI Approved :: MIT License
Classifier: Programming Language :: Python :: 3
Classifier: Programming Language :: Python :: 3.8
Classifier: Programming Language :: Python :: 3.9
